__init__.py
gsheet_player/__init__.py
gsheet_player/file_ops.py
gsheet_player/gsheetPlayer.py
gsheet_player/gsheet_ops.py
gsheet_player-0.2.1.dist-info/METADATA
gsheet_player-0.2.1.dist-info/WHEEL
gsheet_player-0.2.1.dist-info/top_level.txt
gsheet_player-0.2.1.dist-info/RECORD
